holocam/__init__.py
holocam/_c.cp311-win_amd64.pyd
holocam/holocam_thread.py
holocam-1.1.0.data/data/holo_cam.dll
holocam-1.1.0.dist-info/METADATA
holocam-1.1.0.dist-info/WHEEL
holocam-1.1.0.dist-info/top_level.txt
holocam-1.1.0.dist-info/RECORD
