Metadata-Version: 2.4
Name: holocam
Version: 1.1.0
Summary: Python wrapper for the Holo virtual camera for windows 11
Author-email: Simon Doksrød <simondok@stud.ntnu.no>
Requires-Python: >=3.8
Requires-Dist: requests
Requires-Dist: importlib-metadata; python_version < "3.10"
Requires-Dist: numpy
